{
  "address": "Unit 107 - 3503 Gislason Avenue",
  "city": "Coquitlam",
  "sqft": 1588,
  "year": 2021,
  "price": 1100000,
  "fee": 410,
  "bedrooms": 3,
  "bathrooms": 3,
  "parking": 2,
  "propertyTax": 3647,
  "assessment": 1135000,
  "description": "AMAZING ROOFTOP DECK! This bright 3 bed, 3 bath townhome in Burke Mountain offers a rare 600 plus square foot private rooftop retreat complete with a soothing hot tub and open mountain views. It is an inviting space for quiet mornings, outdoor meals, and evening relaxation. Inside you will find 10 foot ceilings, wide plank floors, generous windows, and a well designed kitchen with quartz surfaces, a gas stove, stainless appliances, and a large island. The upper level includes three comfortable bedrooms, a walk in closet, and ensuite in the primary. Year round comfort comes from Heat Pump and forced air heating plus a tankless on demand hot water system. A side by side garage with epoxy flooring and added storage completes this impressive home.",
  "features": [],
  "schools": [
    {
      "name": "Leigh Elementary",
      "rating": 5.4,
      "distance": "0.7 km",
      "type": "0-5"
    },
    {
      "name": "Terry Fox Secondary",
      "rating": 2.9,
      "distance": "3.0 km",
      "type": "9-12"
    }
  ],
  "subArea": "Burke Mountain",
  "parkingType": "garage_double",
  "levels": 3,
  "isEndUnit": false,
  "hasAC": true,
  "rainscreen": true,
  "outdoorSpace": "rooftop",
  "condition": 4,
  "_sourceUrl": "https://housesigma.com/bc/coquitlam-real-estate/107-3503-gislason-avenue/home/XRla7gxaWBP3jEvL?id_listing=LzQ1y50ZqJmYqdeK",
  "_scrapedAt": "2026-01-26T08:11:48.843Z",
  "_rawFile": "107_3503_gislason_avenue_coquitlam_burke_mountain.html",
  "listPrice": 1169000,
  "soldDate": "2025-12-20"
}