{
  "address": "Unit 20 - 1950 Salton Road",
  "city": "Abbotsford",
  "sqft": 1840,
  "year": 2020,
  "price": 753000,
  "listPrice": 750000,
  "fee": 238,
  "bedrooms": 4,
  "bathrooms": 4,
  "parking": 1,
  "propertyTax": 3101,
  "assessment": 748000,
  "description": "Just what you’ve been looking for!! This Beautiful townhouse features 3 bed and 3 bath upstairs and 1 bedroom LEGAL SUITE as a mortgage helper, bringing in $1500/M. Perfect for families or even investors. Great location with walking distance to UFV, Mccallum Junction Shopping centre, and HWY 1 access around the corner. This one won’t last long! OPEN HOUSE JAN 17(1-3pm).",
  "features": [],
  "schools": [],
  "subArea": "Central Abbotsford",
  "soldDate": "2026-02-04",
  "parkingType": "carport",
  "levels": 3,
  "isEndUnit": false,
  "hasAC": false,
  "rainscreen": true,
  "outdoorSpace": "balcony",
  "condition": 3,
  "_sourceUrl": "https://housesigma.com/bc/abbotsford-real-estate/20-1950-salton-road/home/owJKR7PBRQMYXeLP?id_listing=9w8o3mj5wLJYGKjm",
  "_scrapedAt": "2026-03-07T02:29:52.572Z",
  "_rawFile": "20_1950_salton_road_abbotsford_central_abbotsford.html"
}