{
  "address": "Unit 24 - 32970 Tunbridge Avenue",
  "city": "Mission",
  "sqft": 1894,
  "year": 2024,
  "price": 758900,
  "listPrice": 759900,
  "fee": 285,
  "bedrooms": 3,
  "bathrooms": 4,
  "parking": 2,
  "propertyTax": 3241,
  "assessment": 802000,
  "description": "Very solid and well built 3 bedroom 3 storey townhouse with 4 baths. Over 1800 sq ft not included Garage. Excellent location and close to school and transport. Comes with Quartz counter tops , Large kitchen with lots of cabinets,  Appliances and Blinds. Very easy to view with short notice. Very well priced for quick sale. More info please touch base or call.",
  "features": [],
  "schools": [],
  "subArea": "Mission BC",
  "soldDate": "2026-01-24",
  "parkingType": "garage_double",
  "levels": 3,
  "isEndUnit": false,
  "hasAC": true,
  "rainscreen": true,
  "outdoorSpace": "balcony",
  "condition": 4,
  "_sourceUrl": "https://housesigma.com/bc/mission-real-estate/24-32970-tunbridge-avenue/home/JRv53KD4OBPYVPW4?id_listing=eQp5yOw8b8gyd0ZE",
  "_scrapedAt": "2026-02-16T20:49:33.231Z",
  "_rawFile": "24_32970_tunbridge_avenue_mission_mission_bc.html"
}