{
  "address": "Unit 46 - 2351 Parkway Boulevard",
  "city": "Coquitlam",
  "sqft": 2109,
  "year": 2003,
  "price": 950000,
  "fee": 473,
  "bedrooms": 3,
  "bathrooms": 3,
  "parking": 2,
  "propertyTax": 3963,
  "assessment": 1048000,
  "description": "Surrounded by nature’s tranquility and lush greenery, this 3-level townhouse blends generous space with timeless comfort. The main floor welcomes you with updated flooring, a cozy family room, and an open living and dining area that extends to a sunny SE-facing balcony—perfect for summer BBQs. Upstairs, the vaulted primary suite offers complete privacy with a spacious walk-in closet and ensuite, while two additional bedrooms share a well-designed full bathroom—ideal for family living. The adaptable lower level invites you to create your vision: a dream theatre, workout studio, library, or family fun zone. This flexible space is ready to evolve with your lifestyle. Set in a quiet neighbourhood just steps from golf, trails, and parks, yet minutes from schools, shopping, and dining. Call now!",
  "features": [],
  "schools": [
    {
      "name": "Gleneagle Secondary",
      "rating": 6.6,
      "distance": "4.1 km",
      "type": "9-12"
    },
    {
      "name": "Hampton Park Elementary",
      "rating": 6.3,
      "distance": "1.0 km",
      "type": "0-5"
    }
  ],
  "subArea": "Westwood Plateau",
  "parkingType": "garage_double",
  "levels": 1,
  "isEndUnit": false,
  "hasAC": false,
  "rainscreen": false,
  "outdoorSpace": "balcony",
  "condition": 4,
  "_sourceUrl": "https://housesigma.com/bc/coquitlam-real-estate/46-2351-parkway-boulevard/home/GMnKYqpQl0B3w1Qr?id_listing=Vwod7vKDDqj35mGN",
  "_scrapedAt": "2026-01-26T08:26:45.831Z",
  "_rawFile": "46_2351_parkway_boulevard_coquitlam_westwood_plateau.html",
  "listPrice": 999000
}