{
  "address": "Unit 59 - 36060 Old Yale Road",
  "city": "Abbotsford",
  "sqft": 1384,
  "year": 1991,
  "price": 667000,
  "listPrice": 679999,
  "fee": 385,
  "bedrooms": 3,
  "bathrooms": 3,
  "parking": 2,
  "propertyTax": 2616,
  "assessment": 631000,
  "description": "This one checks every box! Fully reno'd, sun-filled, and steps from everything! Modern 3 bd 3 bth Mountain View Village unit featuring wide open floor plan filled with natural light and turn key Aesthetic. New modern kitchen w/ granite countertops, updated baths, fresh paint, new carpet, and striking gas stone fireplace. Thoughtful architectural details include a solid beam feature opening up main living, adding warmth and character throughout. Step outside to private backyard with a 20’ x 14’ deck & 10’ x 12’ gazebo, + gated access to visitor parking and the heated outdoor pool. Major complex updates include roof, gutters & soffits, windows. Large DBL car garage, easy access to extra parking, and close to schools, parks, shopping & HWY access. Pet friendly.",
  "features": [],
  "schools": [],
  "subArea": "Abbotsford East",
  "soldDate": "2026-01-29",
  "parkingType": "garage_double",
  "levels": 1,
  "isEndUnit": false,
  "hasAC": false,
  "rainscreen": false,
  "outdoorSpace": "yard",
  "condition": 5,
  "_sourceUrl": "https://housesigma.com/bc/abbotsford-real-estate/59-36060-old-yale-road/home/PXRla7gkmz57jEvL?id_listing=eVbOYENpoeByx2P0",
  "_scrapedAt": "2026-02-16T20:47:35.031Z",
  "_rawFile": "59_36060_old_yale_road_abbotsford_abbotsford_east.html"
}