{
  "address": "#11 2352 Pitt River Road",
  "city": "Port Coquitlam",
  "sqft": 1748,
  "year": 1988,
  "price": 834000,
  "fee": 420.46,
  "bedrooms": 3,
  "bathrooms": 3,
  "parking": 2,
  "propertyTax": 30002023,
  "description": "Centrally located in a family & pet-friendly community! This well-maintained 3 bedroom, 3 bathroom + rec room townhome offers comfort & convenience. Thoughtfully updated, featuring a fully renovated kitchen with stone  countertops, tile backsplash, stainless steel appliances, modern lighting & gorgeous laminate flooring throughout. Downstairs features a second foyer off the garage & a large rec room or 4th bedroom. Access your private deck  from the kitchen leading down to a fully fenced backyard, perfect for kids, pets, & entertaining. Additional highlights include ample storage, 2 parking, quick access to Lougheed Hwy & Hwy 1, all while just steps to K-12 schools, PoCo Trails, transit, the West Coast Express, shopping & recreation! Enter complex off of Lobb ave.",
  "features": [],
  "subArea": "Mary Hill",
  "_sourceUrl": "https://www.zealty.ca/property/bc/port-coquitlam/11-2352-pitt-river-road-mls_r3069030",
  "_scrapedAt": "2026-01-21T18:02:45.402Z",
  "_rawFile": "_11_2352_pitt_river_road__port_coquitlam__bc__v3c_5y2.html",
  "rainscreen": false,
  "condition": 4,
  "parkingType": "garage_double",
  "levels": 3,
  "isEndUnit": false,
  "hasAC": false,
  "isRainscreened": false,
  "outdoorSpace": "yard"
}