{
  "address": "#16 3470 Highland Drive",
  "city": "Coquitlam",
  "sqft": 1410,
  "year": 2014,
  "price": 928000,
  "fee": 364.24,
  "bedrooms": 3,
  "bathrooms": 3,
  "parking": 3,
  "propertyTax": 35042024,
  "description": "Unique end unit with 3 bedrooms and 2 . 5 baths in Bridlewood by Polygon located in the heart of Burke Mountain. Next to the world-class hiking & biking trails and surrounded by all kinds of parks. Open- concept main floor boasts a beautiful gigantic quartz countertop island and a privately fenced patio past the French- inspired doors . Bonus third parking spot right beside the unit in addition to an upgraded tandem garage means additional indoor space. Lots of upgrades - laminated hallway stairs, wooden shutters on windows, walk-in closet in primary bedroom, built-in storage throughout, epoxy garage floor, and insulated garage door. Enjoy breath taking views from one of the highest units in Bridlewood. Steps from elementary school & bus stop. Perfect location for a family home. A must see",
  "features": [],
  "subArea": "Burke Mountain",
  "_sourceUrl": "https://www.zealty.ca/property/bc/coquitlam/16-3470-highland-drive-mls_r3069980",
  "_scrapedAt": "2026-01-21T05:23:43.674Z",
  "_rawFile": "_16_3470_highland_drive__coquitlam__bc__v3e_0m1.html",
  "rainscreen": false,
  "condition": 4,
  "parkingType": "garage_tandem",
  "levels": 3,
  "isEndUnit": true,
  "hasAC": false,
  "isRainscreened": false,
  "outdoorSpace": "yard"
}